
{"nodes":[
  {
    "id": 0,
    "name": "ЦИМ",
    "size": 20,
    "fixed": false,
    "type": "theater",
    "px": 500,
    "py": 100
  },
  {
    "id": 1,
    "name": "Юлиуш Словацкий",
    "date": "1809-1849",
    "desc": "Поэт и драматург, один их трех «великих певцов» эпохи польского романтизма.",
    "img": "/static/img/sl.png",
    "type": "person",
    "size": 70
  },
   {
    "id": 2,
    "name": "«Lilla Weneda»",
    "type": "play",
    "size": 10
  },
  {
    "id": 3,
    "name": "Станислав Виткевич",
    "desc": "Писатель и художник-экспрессионист, теоретик искусства.",
    "date": "1885-1939",
    "img": "/static/img/vi.png",
    "type": "person",
    "size": 70
  },
  {
    "id": 4,
    "name": "«В маленькой усадьбе»",
    "type": "play",
    "size": 10
  },
  {
    "id": 5,
    "name": "Славомир Мрожек",
    "desc": "Популярный абсурдист, запрещенный в СССР.",
    "date": "1930-2013",
    "img": "/static/img/mr.png",
    "type": "person",
    "size": 70
  },
  {
    "id": 6,
    "name": "Человек",
    "size": 60,
    "fixed": false,
    "type": "theater",
    "px": 300,
    "py": 100
  },
 {
  "id": 7,
    "name": "«В открытом море»",
    "type": "play",
    "size": 10
  },
   {
    "id": 8,
    "name": "«Эмигранты»",
    "type": "play",
    "size": 10
  },
   {
    "id": 9,
    "name": "«Стриптиз»",
    "type": "play",
    "size": 10
  },
   {
    "id": 10,
    "name": "«Вдовы»",
    "type": "play",
    "size": 10
  },
  {
    "id": 11,
    "name": "«Летний день»",
    "type": "play",
    "size": 10
  },
  {
    "id": 12,
    "name": "Молодежный театр на Фонтанке",
    "size": 20,
    "type": "theater",
    "px": 800,
    "py": 100
  },
  {
    "id": 13,
    "name": "«Танго»",
    "type": "play",
    "size": 10
  },
  {
    "id": 14,
    "name": "БДТ",
    "size": 20,
    "type": "theater",
    "px": 200,
    "py": 300
  },
  {
    "id": 15,
    "name": "«Пешком»",
    "type": "play",
    "size": 10
  },
  {
    "id": 16,
    "name": "Фарсы",
    "size": 20,
    "type": "theater",
    "px": 250,
    "py": 300
  },
  {
    "id": 17,
    "name": "Наш театр",
    "size": 20,
    "type": "theater",
    "px": 200,
    "py": 350
  },
  {
    "id": 18,
    "name": "Событие",
    "size": 20,
    "type": "theater",
    "px": 200,
    "py": 400
  },
  {
    "id": 19,
    "name": "Сатирикон",
    "size": 20,
    "type": "theater",
    "px": 200,
    "py": 400
  },
  {
    "id": 20,
    "name": "Ярослав Ивашкевич",
    "desc": "Ивашкевич был главным образом поэтом и писал пьесы о строительстве Польской Народной Республики.",
    "date": "1894-1980",
    "img": "/static/img/iv.png",
    "type": "person",
    "size": 70
  },
  {
    "id": 21,
    "name": "«Идеальный вор»",
    "type": "play",
    "size": 10
  },
  {
    "id": 22,
    "name": "«Лето в Ноане»",
    "type": "play",
    "size": 10
  },
  {
    "id": 23,
    "name": "Театр им. Вахтангова",
    "size": 20,
    "type": "theater",
    "px": 200,
    "py": 400
  },
  {
    "id": 24,
    "name": "Польский театр в Москве",
    "size": 20,
    "type": "theater",
    "px": 200,
    "py": 400
  },
  {
    "id": 25,
    "name": "«Мария Стюарт»",
    "type": "play",
    "size": 10
  },
  {
    "id": 26,
    "name": "Витольд Гомбрович",
    "desc": "Интеллектуал, строивший свои произведения на гротеске и высмеивающий традиции польского общества.",
    "date": "1894-1969",
    "img": "/static/img/go.png",
    "type": "person",
    "size": 70
  },
  {
    "id": 27,
    "name": "«Ивонна, принцесса Бургундская»",
    "type": "play",
    "size": 10
  },
  {
    "id": 28,
    "name": "Эрмитаж",
    "size": 20,
    "type": "theater",
    "px": 200,
    "py": 400
  },
  {
    "id": 29,
    "name": "Красный факел",
    "size": 20,
    "type": "theater",
    "px": 200,
    "py": 400
  },
  {
    "id": 30,
    "name": "МТЦ Вишневый сад",
    "size": 20,
    "type": "theater",
    "px": 200,
    "py": 400
  },
  {
    "id": 31,
    "name": "Театр у Никитских ворот",
    "size": 20,
    "type": "theater",
    "px": 200,
    "py": 400
  },
  {
    "id": 32,
    "name": "«Сапожники»",
    "type": "play",
    "size": 10
  },
  {
    "id": 33,
    "name": "Леон Кручковский",
    "desc": "Общественный деятель, писатель и публицист, последователь соцреализма.",
    "date": "1900-1962",
    "img": "/static/img/kr.png",
    "type": "person",
    "size": 70
  },
  {
    "id": 34,
    "name": "«Немцы»",
    "type": "play",
    "size": 10
  },
  {
    "id": 35,
    "name": "ЧелГУ",
    "size": 20,
    "fixed": false,
    "type": "theater",
    "px": 200,
    "py": 500
  },
  {
    "id": 36,
    "name": "Тадеуш Ружевич",
    "desc": "Один из самых известных польских драматургов XX века, аутсайдер, ставивший диагнозы послевоенной действительности.",
    "date": "1921-2014",
    "img": "/static/img/ru.png",
    "type": "person",
    "size": 70
  },
  {
    "id": 37,
    "name": "«Картотека»",
    "type": "play",
    "size": 10
  },
  {
    "id": 38,
    "name": "Александринский театр",
    "size": 20,
    "fixed": false,
    "type": "theater",
    "px": 200,
    "py": 500
  },
  {
    "id": 39,
    "name": "«Старая женщина высиживает»",
    "type": "play",
    "size": 10
  },
  {
    "id": 40,
    "name": "Тесные связи",
    "size": 20,
    "fixed": false,
    "type": "theater",
    "px": 200,
    "py": 300
  },
  {
    "id": 41,
    "name": "Анджей Стасюк",
    "desc": "Драматург новой волны, скептически относящийся к возможности единения Востока и Запада.",
    "date": "род.1957",
    "img": "/static/img/st.png",
    "type": "person",
    "size": 70
  },
  {
    "id": 42,
    "name": "«Темный лес»",
    "type": "play",
    "size": 10
  },
  {
    "id": 43,
    "name": "МДТ—Театр Европы",
    "size": 20,
    "fixed": false,
    "type": "theater",
    "px": 200,
    "py": 300
  },
  {
    "id": 44,
    "name": "«Ночь»",
    "type": "play",
    "size": 10
  },
  {
    "id": 45,
    "name": "Свободное пространство",
    "size": 20,
    "fixed": false,
    "type": "theater",
    "px": 200,
    "py": 300
  },
  {
    "id": 46,
    "name": "Театр-студия СПбГУ",
    "size": 20,
    "fixed": false,
    "type": "theater",
    "px": 200,
    "py": 300
  },
  {
    "id": 47,
    "name": "Дорота Масловская",
    "desc": "Молодая, но очень популярная писательница, дебютировавшая в женском журнале «Твой стиль» с личным дневником.",
    "date": "род.1983",
    "img": "/static/img/ma.png",
    "type": "person",
    "size": 70
  },
  {
    "id": 48,
    "name": "«Двое бедных румын, говорящих по-польски»",
    "type": "play",
    "size": 10
  },
  {
    "id": 49,
    "name": "Театр драмы им. Ф. Волкова",
    "size": 20,
    "fixed": false,
    "type": "theater",
    "px": 200,
    "py": 300
  },
  {
    "id": 50,
    "name": "Этюд-театр",
    "size": 20,
    "fixed": false,
    "type": "theater",
    "px": 200,
    "py": 300
  },
  {
    "id": 51,
    "name": "Старый дом",
    "size": 20,
    "fixed": false,
    "type": "theater",
    "px": 200,
    "py": 300
  },
   {
    "id": 52,
    "name": "«У нас все хорошо»",
    "type": "play",
    "size": 10
  },
  {
    "id": 53,
    "name": "Пермский Театр-Театр",
    "size": 20,
    "fixed": false,
    "type": "theater",
    "px": 200,
    "py": 300
  },
  {
    "id": 54,
    "name": "ТЮЗ, Саратов",
    "size": 20,
    "fixed": false,
    "type": "theater",
    "px": 200,
    "py": 300
  },
  {
    "id": 55,
    "name": "Габриэля Запольская",
    "desc": "Тексты Запольской — это социальная сатира и критика привычек буржуазного общества.",
    "date": "1857-1921",
    "img": "/static/img/za.png",
    "type": "person",
    "size": 70
  },
    {
    "id": 56,
    "name": "«Мораль пани Дульской»",
    "type": "play",
    "size": 10
  },
  {
    "id": 57,
    "name": "Курский театр драмы",
    "size": 20,
    "fixed": false,
    "type": "theater",
    "px": 200,
    "py": 300
  },
  {
    "id": 58,
    "name": "Театр им.Моссовета",
    "size": 20,
    "fixed": false,
    "type": "theater",
    "px": 200,
    "py": 300
  },
      {
    "id": 59,
    "name": "«Масенькие супружеские преступления»",
    "type": "play",
    "size": 10
  },
  {
    "id": 60,
    "name": "Театр Романа Виктюка",
    "size": 20,
    "fixed": false,
    "type": "theater",
    "px": 200,
    "py": 300
  },
  {
    "id": 61,
    "name": "Ингмар Вилквист",
    "desc": "Профессор Варшавской академии изящных искусств, замдиректора Национальной галереи пишет под этим псевдонимом пьесы, которые ставятся по всей Европе.",
    "date": "1857-1921",
    "img": "/static/img/vq.png",
    "type": "person",
    "size": 70
  },
  {
    "id": 62,
    "name": "«Ночь Гельвера»",
    "type": "play",
    "size": 10
  },
  {
    "id": 63,
    "name": "Театр Комиссаржевской",
    "size": 20,
    "fixed": false,
    "type": "theater",
    "px": 200,
    "py": 300
  },
  {
    "id": 64,
    "name": "Новошахтинский драматический театр",
    "size": 20,
    "fixed": false,
    "type": "theater",
    "px": 200,
    "py": 300
  }
],



"links":[
  {
    "source":0,
    "target":2
  },
  {
    "source":0,
    "target":4
  },
  {
    "source":2,
    "target":1
  },
  {
    "source":4,
    "target":3
  },
  {
    "source":6,
    "target":7
  },
  {
    "source":7,
    "target":5
  },
  {
    "source":6,
    "target":8
  },
  {
    "source":8,
    "target":5
  },
  {
    "source":6,
    "target":9
  },
  {
    "source":9,
    "target":5
  },
  {
    "source":6,
    "target":10
  },
  {
    "source":10,
    "target":5
  },
  {
    "source":6,
    "target":11
  },
  {
    "source":11,
    "target":5
  },
   {
    "source":5,
    "target":13
  },
  {
    "source":12,
    "target":13
  },
  {
    "source":5,
    "target":15
  },
  {
    "source":14,
    "target":15
  },
  {
    "source":9,
    "target":16
  },
  {
    "source":9,
    "target":17
  },
  {
    "source":9,
    "target":18
  },
  {
    "source":14,
    "target":8
  },
  {
    "source":8,
    "target":19
  },
  {
    "source":20,
    "target":21
  },
  {
    "source":21,
    "target":14
  },
  {
    "source":20,
    "target":22
  },
  {
    "source":22,
    "target":23
  },
  {
    "source":1,
    "target":25
  },
  {
    "source":25,
    "target":24
  },
  {
    "source":26,
    "target":27
  },
  {
    "source":27,
    "target":24
  },
  {
    "source":27,
    "target":23
  },
  {
    "source":27,
    "target":28
  },
  {
    "source":27,
    "target":29
  },
  {
    "source":27,
    "target":30
  },
  {
    "source":32,
    "target":3
  },
  {
    "source":32,
    "target":31
  },
  {
    "source":33,
    "target":34
  },
  {
    "source":34,
    "target":35
  },
  {
    "source":36,
    "target":37
  },
  {
    "source":37,
    "target":6
  },
  {
    "source":36,
    "target":39
  },
  {
    "source":38,
    "target":39
  },
  {
    "source":37,
    "target":40
  },
  {
    "source":41,
    "target":42
  },
  {
    "source":43,
    "target":42
  },
  {
    "source":41,
    "target":44
  },
  {
    "source":44,
    "target":45
  },
  {
    "source":44,
    "target":46
  },
  {
    "source":47,
    "target":48
  },
  {
    "source":48,
    "target":49
  },
  {
    "source":48,
    "target":50
  },
  {
    "source":48,
    "target":51
  },
  {
    "source":48,
    "target":52
  },
  {
    "source":52,
    "target":53
  },
  {
    "source":52,
    "target":54
  },
  {
    "source":55,
    "target":56
  },
  {
    "source":56,
    "target":57
  },
  {
    "source":56,
    "target":58
  },
  {
    "source":55,
    "target":59
  },
  {
    "source":59,
    "target":60
  },
  {
    "source":61,
    "target":62
  },
  {
    "source":62,
    "target":63
  },
  {
    "source":62,
    "target":64
  },
  {
    "source":62,
    "target":51
  }
]}